setup.cfg
setup.py
simplebrowser/__init__.py
simplebrowser/browser.py
simplebrowser.egg-info/PKG-INFO
simplebrowser.egg-info/SOURCES.txt
simplebrowser.egg-info/dependency_links.txt
simplebrowser.egg-info/requires.txt
simplebrowser.egg-info/top_level.txt