Metadata-Version: 1.0
Name: simplebrowser
Version: 0.0.1
Summary: Low-level HTTP browser for easier website interaction
Home-page: https://github.com/estilen/simplebrowser
Author: Lukasz Salitra
Author-email: lukasz.salitra@gmail.com
License: MIT
Platform: UNKNOWN
